ip_query/__init__.py
ip_query/ip_query.py
ip_utils/__init__.py
ip_utils/ip_utils.py
ip_utils-3.1.3.dist-info/LICENSE
ip_utils-3.1.3.dist-info/METADATA
ip_utils-3.1.3.dist-info/WHEEL
ip_utils-3.1.3.dist-info/top_level.txt
ip_utils-3.1.3.dist-info/RECORD
